deepview_onnx/__main__.py
deepview_onnx/conversion_onnx.py
deepview_onnx/assets/image.png
deepview_onnx/assets/info.html
deepview_converter_onnx-2.5.24.dist-info/METADATA
deepview_converter_onnx-2.5.24.dist-info/WHEEL
deepview_converter_onnx-2.5.24.dist-info/entry_points.txt
deepview_converter_onnx-2.5.24.dist-info/top_level.txt
deepview_converter_onnx-2.5.24.dist-info/RECORD
