Metadata-Version: 2.1
Name: deepview-converter-onnx
Version: 2.5.24
Summary: DeepView Converter for ONNX
Home-page: https://www.au-zone.com
Author: Au-Zone
Author-email: support@au-zone.com
License: PROPRIETARY
Platform: UNKNOWN
Requires-Dist: deepview-converter (~=2.6.7)
Requires-Dist: onnxruntime (~=1.17.0)
Requires-Dist: tf2onnx (~=1.16.1)
Requires-Dist: keras2onnx (~=1.7.0)
Requires-Dist: tflite2onnx (~=0.4.1)
